README.rst
setup.py
./__init__.py
./field.py
trytond_encrypted_field.egg-info/PKG-INFO
trytond_encrypted_field.egg-info/SOURCES.txt
trytond_encrypted_field.egg-info/dependency_links.txt
trytond_encrypted_field.egg-info/not-zip-safe
trytond_encrypted_field.egg-info/requires.txt
trytond_encrypted_field.egg-info/top_level.txt