Metadata-Version: 1.1
Name: trytond-encrypted-field
Version: 3.4.1.0
Summary: Encrypted fields in tryton
Home-page: https://www.fulfil.io
Author: Fulfil.IO Inc.
Author-email: support@fulfil.io
License: BSD
Platform: UNKNOWN
Classifier: Development Status :: 5 - Production/Stable
Classifier: Environment :: Plugins
Classifier: Intended Audience :: Developers
Classifier: License :: OSI Approved :: BSD License
Classifier: Natural Language :: English
Classifier: Operating System :: OS Independent
Classifier: Programming Language :: Python
Classifier: Topic :: Office/Business
